{
  "buffer": [
    "     @",
    "  "
  ],
  "C1": [
    "   ",
    "   ",
    "    "
  ],
  "C2": [
    "  [] ",
    "  () ",
    "      "
  ],
  "C3": [
    "  ,, ",
    "     ",
    "      "
  ],
  "C4": [
    "       ",
    "  =||= ",
    "        "
  ],
  "C5": [
    "  | ",
    "  S ",
    "  |  "
  ],
  "C6": [
    "  o/ ",
    "  /o ",
    "      "
  ],
  "C7": [
    "    ",
    "  & ",
    "     "
  ],
  "C8": [
    "  , ",
    "   ",
    "     "
  ],
  "C9": [
    "    ",
    " /  ",
    " `   "
  ],
  "C10": [
    "    ",
    "  \\ ",
    "  '  "
  ],
  "C11": [
    "    ",
    "  * ",
    "     "
  ],
  "C12": [
    "    ",
    "  + ",
    "     "
  ],
  "C13": [
    "    ",
    "  , ",
    "     "
  ],
  "C14": [
    "    ",
    "  - ",
    "     "
  ],
  "C15": [
    "    ",
    "  . ",
    "     "
  ],
  "C16": [
    "   / ",
    "  /  ",
    "      "
  ],
  "C17": [
    "    ",
    "  0 ",
    "     "
  ],
  "C18": [
    "    ",
    "  1 ",
    "     "
  ],
  "C19": [
    "    ",
    "  2 ",
    "     "
  ],
  "C20": [
    "    ",
    "  3 ",
    "     "
  ],
  "C21": [
    "    ",
    "  4 ",
    "     "
  ],
  "C22": [
    "    ",
    "  5 ",
    "     "
  ],
  "C23": [
    "    ",
    "  6 ",
    "     "
  ],
  "C24": [
    "    ",
    "  7 ",
    "     "
  ],
  "C25": [
    "    ",
    "  8 ",
    "     "
  ],
  "C26": [
    "    ",
    "  9 ",
    "     "
  ],
  "C27": [
    "    ",
    "  : ",
    "     "
  ],
  "C28": [
    "    ",
    "  ; ",
    "     "
  ],
  "C29": [
    "  / ",
    "  \\ ",
    "     "
  ],
  "C30": [
    "    ",
    "  = ",
    "     "
  ],
  "C31": [
    "  \\ ",
    "  / ",
    "     "
  ],
  "C32": [
    "    ",
    "  ? ",
    "     "
  ],
  "C33": [
    "   _  ",
    "  (a) ",
    "       "
  ],
  "C34": [
    "   _  ",
    "  //\\ ",
    "       "
  ],
  "C35": [
    "   _  ",
    "  [|} ",
    "       "
  ],
  "C36": [
    "   _ ",
    "  (( ",
    "      "
  ],
  "C37": [
    "   _  ",
    "  [|) ",
    "       "
  ],
  "C38": [
    "   __ ",
    "  [|- ",
    "   `-  "
  ],
  "C39": [
    "   __ ",
    "  [|- ",
    "       "
  ],
  "C40": [
    "   __  ",
    "  (|_; ",
    "        "
  ],
  "C41": [
    "       ",
    "  []-| ",
    "        "
  ],
  "C42": [
    "  () ",
    "  [] ",
    "      "
  ],
  "C43": [
    "   () ",
    "   || ",
    "  [_|  "
  ],
  "C44": [
    "      ",
    "  []/ ",
    "    `  "
  ],
  "C45": [
    "  ||  ",
    "  L_] ",
    "       "
  ],
  "C46": [
    "   _ _  ",
    "  //\\/\\ ",
    "         "
  ],
  "C47": [
    "   _   ",
    "  [|\\| ",
    "        "
  ],
  "C48": [
    "   _  ",
    "  (() ",
    "       "
  ],
  "C49": [
    "   _  ",
    "  ||) ",
    "  L|   "
  ],
  "C50": [
    "   _  ",
    "  (() ",
    "    `  "
  ],
  "C51": [
    "   _  ",
    "  [|) ",
    "    `  "
  ],
  "C52": [
    "     ",
    "  (( ",
    "  ''  "
  ],
  "C53": [
    "  ____ ",
    "   L|  ",
    "        "
  ],
  "C54": [
    "      ",
    "  |U| ",
    "  `-'  "
  ],
  "C55": [
    "  _ _ ",
    "  \\\\/ ",
    "       "
  ],
  "C56": [
    "  _ _ _ ",
    "  \\\\/\\/ ",
    "         "
  ],
  "C57": [
    "      ",
    "  \\\\/ ",
    "  ''`  "
  ],
  "C58": [
    "  _ _ ",
    "  \\\\/ ",
    "  ''   "
  ],
  "C59": [
    "  __  ",
    "  //_ ",
    "       "
  ],
  "C60": [
    "  _  ",
    " |   ",
    " |_   "
  ],
  "C61": [
    "  \\  ",
    "   \\ ",
    "      "
  ],
  "C62": [
    "  _  ",
    "   | ",
    "  _|  "
  ],
  "C63": [
    "  ^ ",
    "   ",
    "     "
  ],
  "C64": [
    "     ",
    "   ",
    "  ==  "
  ],
  "C65": [
    "  . ",
    "   ",
    "     "
  ],
  "C66": [
    "    ",
    "  a ",
    "     "
  ],
  "C67": [
    "    ",
    "  b ",
    "     "
  ],
  "C68": [
    "    ",
    "  c ",
    "     "
  ],
  "C69": [
    "    ",
    "  d ",
    "     "
  ],
  "C70": [
    "    ",
    "  e ",
    "     "
  ],
  "C71": [
    "    ",
    "  f ",
    "     "
  ],
  "C72": [
    "    ",
    "  g ",
    "     "
  ],
  "C73": [
    "    ",
    "  h ",
    "     "
  ],
  "C74": [
    "    ",
    "  i ",
    "     "
  ],
  "C75": [
    "    ",
    "  j ",
    "     "
  ],
  "C76": [
    "    ",
    "  k ",
    "     "
  ],
  "C77": [
    "    ",
    "  l ",
    "     "
  ],
  "C78": [
    "    ",
    "  m ",
    "     "
  ],
  "C79": [
    "    ",
    "  n ",
    "     "
  ],
  "C80": [
    "    ",
    "  o ",
    "     "
  ],
  "C81": [
    "    ",
    "  p ",
    "     "
  ],
  "C82": [
    "    ",
    "  q ",
    "     "
  ],
  "C83": [
    "    ",
    "  r ",
    "     "
  ],
  "C84": [
    "    ",
    "  s ",
    "     "
  ],
  "C85": [
    "    ",
    "  t ",
    "     "
  ],
  "C86": [
    "    ",
    "  u ",
    "     "
  ],
  "C87": [
    "    ",
    "  v ",
    "     "
  ],
  "C88": [
    "    ",
    "  w ",
    "     "
  ],
  "C89": [
    "    ",
    "  x ",
    "     "
  ],
  "C90": [
    "    ",
    "  y ",
    "     "
  ],
  "C91": [
    "    ",
    "  z ",
    "     "
  ],
  "C92": [
    "    ",
    "  { ",
    "     "
  ],
  "C93": [
    "  | ",
    "  | ",
    "  |  "
  ],
  "C94": [
    "    ",
    "  } ",
    "     "
  ],
  "C95": [
    "    ",
    "  ~ ",
    "     "
  ],
  "C96": [
    "   .. ",
    "  //\\ ",
    "       "
  ],
  "C97": [
    "   .. ",
    "  (() ",
    "       "
  ],
  "C98": [
    "   .. ",
    "  |U| ",
    "  `-'  "
  ],
  "C99": [
    "  .. ",
    "  a  ",
    "      "
  ],
  "C100": [
    "  .. ",
    "  o  ",
    "      "
  ],
  "C101": [
    "  .. ",
    "  u  ",
    "      "
  ],
  "C102": [
    "   _  ",
    "  ||} ",
    "  L|   "
  ],
  "C103": [
    "  160",
    "   ",
    "   "
  ],
  "C104": [
    "   @",
    "  161",
    "  () "
  ],
  "C105": [
    "  || ",
    "  L| @",
    "  168"
  ],
  "C106": [
    "  .. ",
    "   ",
    "      "
  ],
  "C107": [
    "  183",
    "  o ",
    "   "
  ],
  "C108": [
    "    @",
    "  192",
    "   `  "
  ],
  "C109": [
    "  //\\ ",
    "      @",
    "  193"
  ],
  "C110": [
    "   '  ",
    "  //\\ ",
    "       "
  ],
  "C111": [
    "  194",
    "   ^  ",
    "  //\\ "
  ],
  "C112": [
    "      @",
    "  195",
    "   ~  "
  ],
  "C113": [
    "  //\\ ",
    "      @",
    "  196"
  ],
  "C114": [
    "   .. ",
    "  //\\ ",
    "       "
  ],
  "C115": [
    "  197",
    "   o  ",
    "  //\\ "
  ],
  "C116": [
    "      @",
    "  198",
    "   ____ "
  ],
  "C117": [
    "  //\\|- ",
    "     `- @",
    "  199"
  ],
  "C118": [
    "     ",
    "  (( ",
    "   '  "
  ],
  "C119": [
    "  200",
    "   `_ ",
    "  ||- "
  ],
  "C120": [
    "   `- @",
    "  201",
    "   '_ "
  ],
  "C121": [
    "  ||- ",
    "   `- @",
    "  202"
  ],
  "C122": [
    "   ^_ ",
    "  ||- ",
    "   `-  "
  ],
  "C123": [
    "  203",
    "   .. ",
    "  ||- "
  ],
  "C124": [
    "   `- @",
    "  204",
    "  `  "
  ],
  "C125": [
    "  L| ",
    "     @",
    "  205"
  ],
  "C126": [
    "   ' ",
    "  L| ",
    "      "
  ],
  "C127": [
    "  206",
    "  ^  ",
    "  L| "
  ],
  "C128": [
    "     @",
    "  207",
    "  .. "
  ],
  "C129": [
    "  L| ",
    "     @",
    "  209"
  ],
  "C130": [
    "   _~  ",
    "  [|\\| ",
    "        "
  ],
  "C131": [
    "  210",
    "   `  ",
    "  (() "
  ],
  "C132": [
    "      @",
    "  211",
    "   '  "
  ],
  "C133": [
    "  (() ",
    "      @",
    "  212"
  ],
  "C134": [
    "   ^  ",
    "  (() ",
    "       "
  ],
  "C135": [
    "  213",
    "   ~  ",
    "  (() "
  ],
  "C136": [
    "      @",
    "  214",
    "   .. "
  ],
  "C137": [
    "  (() ",
    "      @",
    "  217"
  ],
  "C138": [
    "   `  ",
    "  |U| ",
    "  `-'  "
  ],
  "C139": [
    "  218",
    "   '  ",
    "  |U| "
  ],
  "C140": [
    "  `-' @",
    "  219",
    "   ^  "
  ],
  "C141": [
    "  |U| ",
    "  `-' @",
    "  220"
  ],
  "C142": [
    "   .. ",
    "  |U| ",
    "  `-'  "
  ],
  "C143": [
    "  223",
    "   _  ",
    "  ||} "
  ],
  "C144": [
    "  L|  @",
    "  224",
    "  - "
  ],
  "C145": [
    "  a ",
    "    @",
    "  225"
  ],
  "C146": [
    "  , ",
    "  a ",
    "     "
  ],
  "C147": [
    "  226",
    "  ^ ",
    "  a "
  ],
  "C148": [
    "    @",
    "  227",
    "  ~ "
  ],
  "C149": [
    "  a ",
    "    @",
    "  228"
  ],
  "C150": [
    "  .. ",
    "  a  ",
    "      "
  ],
  "C151": [
    "  229",
    "  . ",
    "  a "
  ],
  "C152": [
    "    @",
    "  231",
    "    "
  ],
  "C153": [
    "  c ",
    "  ' @",
    "  232"
  ],
  "C154": [
    "  - ",
    "  e ",
    "     "
  ],
  "C155": [
    "  233",
    "  , ",
    "  e "
  ],
  "C156": [
    "    @",
    "  234",
    "  ^ "
  ],
  "C157": [
    "  e ",
    "    @",
    "  235"
  ],
  "C158": [
    "  .. ",
    "  e  ",
    "      "
  ],
  "C159": [
    "  236",
    "  - ",
    "  i "
  ],
  "C160": [
    "    @",
    "  237",
    "  , "
  ],
  "C161": [
    "  i ",
    "    @",
    "  238"
  ],
  "C162": [
    "  ^ ",
    "  i ",
    "     "
  ],
  "C163": [
    "  239",
    "  .. ",
    "  i  "
  ],
  "C164": [
    "     @",
    "  241",
    "  ~ "
  ],
  "C165": [
    "  n ",
    "    @",
    "  242"
  ],
  "C166": [
    "  - ",
    "  o ",
    "     "
  ],
  "C167": [
    "  243",
    "  , ",
    "  o "
  ],
  "C168": [
    "    @",
    "  244",
    "  ^ "
  ],
  "C169": [
    "  o ",
    "    @",
    "  245"
  ],
  "C170": [
    "  ~ ",
    "  o ",
    "     "
  ],
  "C171": [
    "  246",
    "  .. ",
    "  o  "
  ],
  "C172": [
    "     @",
    "  249",
    "  - "
  ],
  "C173": [
    "  u ",
    "    @",
    "  250"
  ],
  "C174": [
    "  , ",
    "  u ",
    "     "
  ],
  "C175": [
    "  251",
    "  ^ ",
    "  u "
  ],
  "C176": [
    "    @",
    "  252",
    "  .. "
  ],
  "C177": [
    "  u  ",
    "     @",
    "  253"
  ],
  "C178": [
    "  , ",
    "  y ",
    "     "
  ],
  "C179": [
    "  255",
    "  .. ",
    "  y  "
  ]
}