{
  "buffer": [
    "  "
  ],
  "C1": [
    "          ",
    "          ",
    "          ",
    "          ",
    "          ",
    "          ",
    "          ",
    "          ",
    "          ",
    "          ",
    "           "
  ],
  "C2": [
    "   ",
    "   ",
    "   ",
    "   ",
    "   ",
    "   ",
    "   ",
    "   ",
    "   ",
    "   ",
    "    "
  ],
  "C3": [
    "   ",
    "   ",
    "   ",
    "   ",
    "   ",
    "   ",
    "   ",
    "   ",
    "   ",
    "   ",
    "    "
  ],
  "C4": [
    "   ",
    "   ",
    "   ",
    "   ",
    "   ",
    "   ",
    "   ",
    "   ",
    "   ",
    "   ",
    "    "
  ],
  "C5": [
    "   ",
    "   ",
    "   ",
    "   ",
    "   ",
    "   ",
    "   ",
    "   ",
    "   ",
    "   ",
    "    "
  ],
  "C6": [
    "   ",
    "   ",
    "   ",
    "   ",
    "   ",
    "   ",
    "   ",
    "   ",
    "   ",
    "   ",
    "    "
  ],
  "C7": [
    "   ",
    "   ",
    "   ",
    "   ",
    "   ",
    "   ",
    "   ",
    "   ",
    "   ",
    "   ",
    "    "
  ],
  "C8": [
    "   ",
    "   ",
    "   ",
    "   ",
    "   ",
    "   ",
    "   ",
    "   ",
    "   ",
    "   ",
    "    "
  ],
  "C9": [
    "   ",
    "   ",
    "   ",
    "   ",
    "   ",
    "   ",
    "   ",
    "   ",
    "   ",
    "   ",
    "    "
  ],
  "C10": [
    "   ",
    "   ",
    "   ",
    "   ",
    "   ",
    "   ",
    "   ",
    "   ",
    "   ",
    "   ",
    "    "
  ],
  "C11": [
    "   ",
    "   ",
    "   ",
    "   ",
    "   ",
    "   ",
    "   ",
    "   ",
    "   ",
    "   ",
    "    "
  ],
  "C12": [
    "   ",
    "   ",
    "   ",
    "   ",
    "   ",
    "   ",
    "   ",
    "   ",
    "   ",
    "   ",
    "    "
  ],
  "C13": [
    "   ",
    "   ",
    "   ",
    "   ",
    "   ",
    "   ",
    "   ",
    "   ",
    "   ",
    "   ",
    "    "
  ],
  "C14": [
    "   ",
    "   ",
    "   ",
    "   ",
    "   ",
    "   ",
    "   ",
    "   ",
    "   ",
    "   ",
    "    "
  ],
  "C15": [
    "   ",
    "   ",
    "   ",
    "   ",
    "   ",
    "   ",
    "   ",
    "   ",
    "   ",
    "   ",
    "    "
  ],
  "C16": [
    "   ",
    "   ",
    "   ",
    "   ",
    "   ",
    "   ",
    "   ",
    "   ",
    "   ",
    "   ",
    "    "
  ],
  "C17": [
    "   ",
    "   ",
    "   ",
    "   ",
    "   ",
    "   ",
    "   ",
    "   ",
    "   ",
    "   ",
    "    "
  ],
  "C18": [
    "   ",
    "   ",
    "   ",
    "   ",
    "   ",
    "   ",
    "   ",
    "   ",
    "   ",
    "   ",
    "    "
  ],
  "C19": [
    "   ",
    "   ",
    "   ",
    "   ",
    "   ",
    "   ",
    "   ",
    "   ",
    "   ",
    "   ",
    "    "
  ],
  "C20": [
    "   ",
    "   ",
    "   ",
    "   ",
    "   ",
    "   ",
    "   ",
    "   ",
    "   ",
    "   ",
    "    "
  ],
  "C21": [
    "   ",
    "   ",
    "   ",
    "   ",
    "   ",
    "   ",
    "   ",
    "   ",
    "   ",
    "   ",
    "    "
  ],
  "C22": [
    "   ",
    "   ",
    "   ",
    "   ",
    "   ",
    "   ",
    "   ",
    "   ",
    "   ",
    "   ",
    "    "
  ],
  "C23": [
    "   ",
    "   ",
    "   ",
    "   ",
    "   ",
    "   ",
    "   ",
    "   ",
    "   ",
    "   ",
    "    "
  ],
  "C24": [
    "   ",
    "   ",
    "   ",
    "   ",
    "   ",
    "   ",
    "   ",
    "   ",
    "   ",
    "   ",
    "    "
  ],
  "C25": [
    "   ",
    "   ",
    "   ",
    "   ",
    "   ",
    "   ",
    "   ",
    "   ",
    "   ",
    "   ",
    "    "
  ],
  "C26": [
    "   ",
    "   ",
    "   ",
    "   ",
    "   ",
    "   ",
    "   ",
    "   ",
    "   ",
    "   ",
    "    "
  ],
  "C27": [
    "   ",
    "   ",
    "   ",
    "   ",
    "   ",
    "   ",
    "   ",
    "   ",
    "   ",
    "   ",
    "    "
  ],
  "C28": [
    "   ",
    "   ",
    "   ",
    "   ",
    "   ",
    "   ",
    "   ",
    "   ",
    "   ",
    "   ",
    "    "
  ],
  "C29": [
    "   ",
    "   ",
    "   ",
    "   ",
    "   ",
    "   ",
    "   ",
    "   ",
    "   ",
    "   ",
    "    "
  ],
  "C30": [
    "   ",
    "   ",
    "   ",
    "   ",
    "   ",
    "   ",
    "   ",
    "   ",
    "   ",
    "   ",
    "    "
  ],
  "C31": [
    "   ",
    "   ",
    "   ",
    "   ",
    "   ",
    "   ",
    "   ",
    "   ",
    "   ",
    "   ",
    "    "
  ],
  "C32": [
    "   ",
    "   ",
    "   ",
    "   ",
    "   ",
    "   ",
    "   ",
    "   ",
    "   ",
    "   ",
    "    "
  ],
  "C33": [
    "   ",
    "   ",
    "   ",
    "   ",
    "   ",
    "   ",
    "   ",
    "   ",
    "   ",
    "   ",
    "    "
  ],
  "C34": [
    "        ___      ",
    "       /\\  \\     ",
    "      /::\\  \\    ",
    "     /:/\\:\\  \\   ",
    "    /:/ /::\\  \\  ",
    "   /:/_/:/\\:\\__\\ ",
    "   \\:\\/:/  \\/__/ ",
    "    \\::/__/      ",
    "     \\:\\  \\      ",
    "      \\:\\__\\     ",
    "       \\/__/      "
  ],
  "C35": [
    "                 ",
    "       _____     ",
    "      /::\\  \\    ",
    "     /:/\\:\\  \\   ",
    "    /:/ /::\\__\\  ",
    "   /:/_/:/\\:|__| ",
    "   \\:\\/:/ /:/  / ",
    "    \\::/_/:/  /  ",
    "     \\:\\/:/  /   ",
    "      \\::/  /    ",
    "       \\/__/      "
  ],
  "C36": [
    "        ___      ",
    "       /\\__\\     ",
    "      /:/  /     ",
    "     /:/  /      ",
    "    /:/  /  ___  ",
    "   /:/__/  /\\__\\ ",
    "   \\:\\  \\ /:/  / ",
    "    \\:\\  /:/  /  ",
    "     \\:\\/:/  /   ",
    "      \\::/  /    ",
    "       \\/__/      "
  ],
  "C37": [
    "                 ",
    "       _____     ",
    "      /::\\  \\    ",
    "     /:/\\:\\  \\   ",
    "    /:/  \\:\\__\\  ",
    "   /:/__/ \\:|__| ",
    "   \\:\\  \\ /:/  / ",
    "    \\:\\  /:/  /  ",
    "     \\:\\/:/  /   ",
    "      \\::/  /    ",
    "       \\/__/      "
  ],
  "C38": [
    "        ___      ",
    "       /\\__\\     ",
    "      /:/ _/_    ",
    "     /:/ /\\__\\   ",
    "    /:/ /:/ _/_  ",
    "   /:/_/:/ /\\__\\ ",
    "   \\:\\/:/ /:/  / ",
    "    \\::/_/:/  /  ",
    "     \\:\\/:/  /   ",
    "      \\::/  /    ",
    "       \\/__/      "
  ],
  "C39": [
    "        ___      ",
    "       /\\__\\     ",
    "      /:/ _/_    ",
    "     /:/ /\\__\\   ",
    "    /:/ /:/  /   ",
    "   /:/_/:/  /    ",
    "   \\:\\/:/  /     ",
    "    \\::/__/      ",
    "     \\:\\  \\      ",
    "      \\:\\__\\     ",
    "       \\/__/      "
  ],
  "C40": [
    "        ___      ",
    "       /\\__\\     ",
    "      /:/ _/_    ",
    "     /:/ /\\  \\   ",
    "    /:/ /::\\  \\  ",
    "   /:/__\\/\\:\\__\\ ",
    "   \\:\\  \\ /:/  / ",
    "    \\:\\  /:/  /  ",
    "     \\:\\/:/  /   ",
    "      \\::/  /    ",
    "       \\/__/      "
  ],
  "C41": [
    "        ___      ",
    "       /\\  \\     ",
    "       \\:\\  \\    ",
    "        \\:\\  \\   ",
    "    ___ /::\\  \\  ",
    "   /\\  /:/\\:\\__\\ ",
    "   \\:\\/:/  \\/__/ ",
    "    \\::/__/      ",
    "     \\:\\  \\      ",
    "      \\:\\__\\     ",
    "       \\/__/      "
  ],
  "C42": [
    "               ",
    "               ",
    "      ___      ",
    "     /\\__\\     ",
    "    /:/__/     ",
    "   /::\\  \\     ",
    "   \\/\\:\\  \\__  ",
    "    ~~\\:\\/\\__\\ ",
    "       \\::/  / ",
    "       /:/  /  ",
    "       \\/__/    "
  ],
  "C43": [
    "              ",
    "      ___     ",
    "     /\\__\\    ",
    "    /:/__/    ",
    "   /::\\  \\    ",
    "   \\/\\:\\  \\   ",
    "    ~~\\:\\  \\  ",
    "       \\:\\__\\ ",
    "       /:/  / ",
    "      /:/  /  ",
    "      \\/__/    "
  ],
  "C44": [
    "        ___      ",
    "       /|  |     ",
    "      |:|  |     ",
    "      |:|  |     ",
    "    __|:|  |     ",
    "   /\\ |:|__|____ ",
    "   \\:\\/:::::/__/ ",
    "    \\::/~~/~     ",
    "     \\:\\~~\\      ",
    "      \\:\\__\\     ",
    "       \\/__/      "
  ],
  "C45": [
    "                 ",
    "                 ",
    "                 ",
    "                 ",
    "    ___     ___  ",
    "   /\\  \\   /\\__\\ ",
    "   \\:\\  \\ /:/  / ",
    "    \\:\\  /:/  /  ",
    "     \\:\\/:/  /   ",
    "      \\::/  /    ",
    "       \\/__/      "
  ],
  "C46": [
    "        ___      ",
    "       /\\  \\     ",
    "      |::\\  \\    ",
    "      |:|:\\  \\   ",
    "    __|:|\\:\\  \\  ",
    "   /::::|_\\:\\__\\ ",
    "   \\:\\~~\\  \\/__/ ",
    "    \\:\\  \\       ",
    "     \\:\\  \\      ",
    "      \\:\\__\\     ",
    "       \\/__/      "
  ],
  "C47": [
    "        ___      ",
    "       /\\  \\     ",
    "       \\:\\  \\    ",
    "        \\:\\  \\   ",
    "    _____\\:\\  \\  ",
    "   /::::::::\\__\\ ",
    "   \\:\\~~\\~~\\/__/ ",
    "    \\:\\  \\       ",
    "     \\:\\  \\      ",
    "      \\:\\__\\     ",
    "       \\/__/      "
  ],
  "C48": [
    "        ___      ",
    "       /\\  \\     ",
    "      /::\\  \\    ",
    "     /:/\\:\\  \\   ",
    "    /:/  \\:\\  \\  ",
    "   /:/__/ \\:\\__\\ ",
    "   \\:\\  \\ /:/  / ",
    "    \\:\\  /:/  /  ",
    "     \\:\\/:/  /   ",
    "      \\::/  /    ",
    "       \\/__/      "
  ],
  "C49": [
    "        ___    ",
    "       /\\  \\   ",
    "      /::\\  \\  ",
    "     /:/\\:\\__\\ ",
    "    /:/ /:/  / ",
    "   /:/_/:/  /  ",
    "   \\:\\/:/  /   ",
    "    \\::/__/    ",
    "     \\:\\  \\    ",
    "      \\:\\__\\   ",
    "       \\/__/    "
  ],
  "C50": [
    "                 ",
    "                 ",
    "        ___      ",
    "       /\\  \\     ",
    "      /::\\  \\    ",
    "     /:/\\:\\  \\   ",
    "    /:/ /::\\  \\  ",
    "   /:/_/:/\\:\\__\\ ",
    "   \\:\\/:/  \\/__/ ",
    "    \\::/  /      ",
    "     \\/__/        "
  ],
  "C51": [
    "        ___      ",
    "       /\\  \\     ",
    "      /::\\  \\    ",
    "     /:/\\:\\__\\   ",
    "    /:/ /:/  /   ",
    "   /:/_/:/__/___ ",
    "   \\:\\/:::::/  / ",
    "    \\::/~~/~~~~  ",
    "     \\:\\~~\\      ",
    "      \\:\\__\\     ",
    "       \\/__/      "
  ],
  "C52": [
    "        ___      ",
    "       /\\__\\     ",
    "      /:/ _/_    ",
    "     /:/ /\\  \\   ",
    "    /:/ /::\\  \\  ",
    "   /:/_/:/\\:\\__\\ ",
    "   \\:\\/:/ /:/  / ",
    "    \\::/ /:/  /  ",
    "     \\/_/:/  /   ",
    "       /:/  /    ",
    "       \\/__/      "
  ],
  "C53": [
    "                 ",
    "                 ",
    "        ___      ",
    "       /\\__\\     ",
    "      /:/  /     ",
    "     /:/__/      ",
    "    /::\\  \\      ",
    "   /:/\\:\\  \\     ",
    "   \\/__\\:\\  \\    ",
    "        \\:\\__\\   ",
    "         \\/__/    "
  ],
  "C54": [
    "        ___      ",
    "       /\\  \\     ",
    "       \\:\\  \\    ",
    "        \\:\\  \\   ",
    "    ___  \\:\\  \\  ",
    "   /\\  \\  \\:\\__\\ ",
    "   \\:\\  \\ /:/  / ",
    "    \\:\\  /:/  /  ",
    "     \\:\\/:/  /   ",
    "      \\::/  /    ",
    "       \\/__/      "
  ],
  "C55": [
    "                 ",
    "        ___      ",
    "       /\\  \\     ",
    "       \\:\\  \\    ",
    "        \\:\\  \\   ",
    "    ___  \\:\\__\\  ",
    "   /\\  \\ |:|  |  ",
    "   \\:\\  \\|:|  |  ",
    "    \\:\\__|:|__|  ",
    "     \\::::/__/   ",
    "      ~~~~        "
  ],
  "C56": [
    "        ___      ",
    "       /\\  \\     ",
    "      _\\:\\  \\    ",
    "     /\\ \\:\\  \\   ",
    "    _\\:\\ \\:\\  \\  ",
    "   /\\ \\:\\ \\:\\__\\ ",
    "   \\:\\ \\:\\/:/  / ",
    "    \\:\\ \\::/  /  ",
    "     \\:\\/:/  /   ",
    "      \\::/  /    ",
    "       \\/__/      "
  ],
  "C57": [
    "        ___       ",
    "       /|  |      ",
    "      |:|  |      ",
    "      |:|  |      ",
    "    __|:|__|      ",
    "   /::::\\__\\_____ ",
    "   ~~~~\\::::/___/ ",
    "       |:|~~|     ",
    "       |:|  |     ",
    "       |:|__|     ",
    "       |/__/       "
  ],
  "C58": [
    "               ",
    "               ",
    "        ___    ",
    "       /|  |   ",
    "      |:|  |   ",
    "      |:|  |   ",
    "    __|:|__|   ",
    "   /::::\\  \\   ",
    "   ~~~~\\:\\  \\  ",
    "        \\:\\__\\ ",
    "         \\/__/  "
  ],
  "C59": [
    "        ___      ",
    "       /\\__\\     ",
    "      /::|  |    ",
    "     /:/:|  |    ",
    "    /:/|:|  |__  ",
    "   /:/ |:| /\\__\\ ",
    "   \\/__|:|/:/  / ",
    "       |:/:/  /  ",
    "       |::/  /   ",
    "       |:/  /    ",
    "       |/__/      "
  ],
  "C60": [
    "        ___      ",
    "       /\\  \\     ",
    "      /::\\  \\    ",
    "     /::::\\  \\   ",
    "    /::::::\\  \\  ",
    "   /:::LS:::\\__\\ ",
    "   \\::1994::/  / ",
    "    \\::::::/  /  ",
    "     \\::::/  /   ",
    "      \\::/  /    ",
    "       \\/__/      "
  ],
  "C61": [
    "   ",
    "   ",
    "   ",
    "   ",
    "   ",
    "   ",
    "   ",
    "   ",
    "   ",
    "   ",
    "    "
  ],
  "C62": [
    "   ",
    "   ",
    "   ",
    "   ",
    "   ",
    "   ",
    "   ",
    "   ",
    "   ",
    "   ",
    "    "
  ],
  "C63": [
    "   ",
    "   ",
    "   ",
    "   ",
    "   ",
    "   ",
    "   ",
    "   ",
    "   ",
    "   ",
    "    "
  ],
  "C64": [
    "   ",
    "   ",
    "   ",
    "   ",
    "   ",
    "   ",
    "   ",
    "   ",
    "   ",
    "   ",
    "    "
  ],
  "C65": [
    "   ",
    "   ",
    "   ",
    "   ",
    "   ",
    "   ",
    "   ",
    "   ",
    "   ",
    "   ",
    "    "
  ],
  "C66": [
    "        ___      ",
    "       /\\  \\     ",
    "      /::\\  \\    ",
    "     /:/\\:\\  \\   ",
    "    /:/ /::\\  \\  ",
    "   /:/_/:/\\:\\__\\ ",
    "   \\:\\/:/  \\/__/ ",
    "    \\::/__/      ",
    "     \\:\\  \\      ",
    "      \\:\\__\\     ",
    "       \\/__/      "
  ],
  "C67": [
    "                 ",
    "       _____     ",
    "      /::\\  \\    ",
    "     /:/\\:\\  \\   ",
    "    /:/ /::\\__\\  ",
    "   /:/_/:/\\:|__| ",
    "   \\:\\/:/ /:/  / ",
    "    \\::/_/:/  /  ",
    "     \\:\\/:/  /   ",
    "      \\::/  /    ",
    "       \\/__/      "
  ],
  "C68": [
    "        ___      ",
    "       /\\__\\     ",
    "      /:/  /     ",
    "     /:/  /      ",
    "    /:/  /  ___  ",
    "   /:/__/  /\\__\\ ",
    "   \\:\\  \\ /:/  / ",
    "    \\:\\  /:/  /  ",
    "     \\:\\/:/  /   ",
    "      \\::/  /    ",
    "       \\/__/      "
  ],
  "C69": [
    "                 ",
    "       _____     ",
    "      /::\\  \\    ",
    "     /:/\\:\\  \\   ",
    "    /:/  \\:\\__\\  ",
    "   /:/__/ \\:|__| ",
    "   \\:\\  \\ /:/  / ",
    "    \\:\\  /:/  /  ",
    "     \\:\\/:/  /   ",
    "      \\::/  /    ",
    "       \\/__/      "
  ],
  "C70": [
    "        ___      ",
    "       /\\__\\     ",
    "      /:/ _/_    ",
    "     /:/ /\\__\\   ",
    "    /:/ /:/ _/_  ",
    "   /:/_/:/ /\\__\\ ",
    "   \\:\\/:/ /:/  / ",
    "    \\::/_/:/  /  ",
    "     \\:\\/:/  /   ",
    "      \\::/  /    ",
    "       \\/__/      "
  ],
  "C71": [
    "        ___      ",
    "       /\\__\\     ",
    "      /:/ _/_    ",
    "     /:/ /\\__\\   ",
    "    /:/ /:/  /   ",
    "   /:/_/:/  /    ",
    "   \\:\\/:/  /     ",
    "    \\::/__/      ",
    "     \\:\\  \\      ",
    "      \\:\\__\\     ",
    "       \\/__/      "
  ],
  "C72": [
    "        ___      ",
    "       /\\__\\     ",
    "      /:/ _/_    ",
    "     /:/ /\\  \\   ",
    "    /:/ /::\\  \\  ",
    "   /:/__\\/\\:\\__\\ ",
    "   \\:\\  \\ /:/  / ",
    "    \\:\\  /:/  /  ",
    "     \\:\\/:/  /   ",
    "      \\::/  /    ",
    "       \\/__/      "
  ],
  "C73": [
    "        ___      ",
    "       /\\  \\     ",
    "       \\:\\  \\    ",
    "        \\:\\  \\   ",
    "    ___ /::\\  \\  ",
    "   /\\  /:/\\:\\__\\ ",
    "   \\:\\/:/  \\/__/ ",
    "    \\::/__/      ",
    "     \\:\\  \\      ",
    "      \\:\\__\\     ",
    "       \\/__/      "
  ],
  "C74": [
    "               ",
    "               ",
    "      ___      ",
    "     /\\__\\     ",
    "    /:/__/     ",
    "   /::\\  \\     ",
    "   \\/\\:\\  \\__  ",
    "    ~~\\:\\/\\__\\ ",
    "       \\::/  / ",
    "       /:/  /  ",
    "       \\/__/    "
  ],
  "C75": [
    "              ",
    "      ___     ",
    "     /\\__\\    ",
    "    /:/__/    ",
    "   /::\\  \\    ",
    "   \\/\\:\\  \\   ",
    "    ~~\\:\\  \\  ",
    "       \\:\\__\\ ",
    "       /:/  / ",
    "      /:/  /  ",
    "      \\/__/    "
  ],
  "C76": [
    "        ___      ",
    "       /|  |     ",
    "      |:|  |     ",
    "      |:|  |     ",
    "    __|:|  |     ",
    "   /\\ |:|__|____ ",
    "   \\:\\/:::::/__/ ",
    "    \\::/~~/~     ",
    "     \\:\\~~\\      ",
    "      \\:\\__\\     ",
    "       \\/__/      "
  ],
  "C77": [
    "                 ",
    "                 ",
    "                 ",
    "                 ",
    "    ___     ___  ",
    "   /\\  \\   /\\__\\ ",
    "   \\:\\  \\ /:/  / ",
    "    \\:\\  /:/  /  ",
    "     \\:\\/:/  /   ",
    "      \\::/  /    ",
    "       \\/__/      "
  ],
  "C78": [
    "        ___      ",
    "       /\\  \\     ",
    "      |::\\  \\    ",
    "      |:|:\\  \\   ",
    "    __|:|\\:\\  \\  ",
    "   /::::|_\\:\\__\\ ",
    "   \\:\\~~\\  \\/__/ ",
    "    \\:\\  \\       ",
    "     \\:\\  \\      ",
    "      \\:\\__\\     ",
    "       \\/__/      "
  ],
  "C79": [
    "        ___      ",
    "       /\\  \\     ",
    "       \\:\\  \\    ",
    "        \\:\\  \\   ",
    "    _____\\:\\  \\  ",
    "   /::::::::\\__\\ ",
    "   \\:\\~~\\~~\\/__/ ",
    "    \\:\\  \\       ",
    "     \\:\\  \\      ",
    "      \\:\\__\\     ",
    "       \\/__/      "
  ],
  "C80": [
    "        ___      ",
    "       /\\  \\     ",
    "      /::\\  \\    ",
    "     /:/\\:\\  \\   ",
    "    /:/  \\:\\  \\  ",
    "   /:/__/ \\:\\__\\ ",
    "   \\:\\  \\ /:/  / ",
    "    \\:\\  /:/  /  ",
    "     \\:\\/:/  /   ",
    "      \\::/  /    ",
    "       \\/__/      "
  ],
  "C81": [
    "        ___    ",
    "       /\\  \\   ",
    "      /::\\  \\  ",
    "     /:/\\:\\__\\ ",
    "    /:/ /:/  / ",
    "   /:/_/:/  /  ",
    "   \\:\\/:/  /   ",
    "    \\::/__/    ",
    "     \\:\\  \\    ",
    "      \\:\\__\\   ",
    "       \\/__/    "
  ],
  "C82": [
    "                 ",
    "                 ",
    "        ___      ",
    "       /\\  \\     ",
    "      /::\\  \\    ",
    "     /:/\\:\\  \\   ",
    "    /:/ /::\\  \\  ",
    "   /:/_/:/\\:\\__\\ ",
    "   \\:\\/:/  \\/__/ ",
    "    \\::/  /      ",
    "     \\/__/        "
  ],
  "C83": [
    "        ___      ",
    "       /\\  \\     ",
    "      /::\\  \\    ",
    "     /:/\\:\\__\\   ",
    "    /:/ /:/  /   ",
    "   /:/_/:/__/___ ",
    "   \\:\\/:::::/  / ",
    "    \\::/~~/~~~~  ",
    "     \\:\\~~\\      ",
    "      \\:\\__\\     ",
    "       \\/__/      "
  ],
  "C84": [
    "        ___      ",
    "       /\\__\\     ",
    "      /:/ _/_    ",
    "     /:/ /\\  \\   ",
    "    /:/ /::\\  \\  ",
    "   /:/_/:/\\:\\__\\ ",
    "   \\:\\/:/ /:/  / ",
    "    \\::/ /:/  /  ",
    "     \\/_/:/  /   ",
    "       /:/  /    ",
    "       \\/__/      "
  ],
  "C85": [
    "                 ",
    "                 ",
    "        ___      ",
    "       /\\__\\     ",
    "      /:/  /     ",
    "     /:/__/      ",
    "    /::\\  \\      ",
    "   /:/\\:\\  \\     ",
    "   \\/__\\:\\  \\    ",
    "        \\:\\__\\   ",
    "         \\/__/    "
  ],
  "C86": [
    "        ___      ",
    "       /\\  \\     ",
    "       \\:\\  \\    ",
    "        \\:\\  \\   ",
    "    ___  \\:\\  \\  ",
    "   /\\  \\  \\:\\__\\ ",
    "   \\:\\  \\ /:/  / ",
    "    \\:\\  /:/  /  ",
    "     \\:\\/:/  /   ",
    "      \\::/  /    ",
    "       \\/__/      "
  ],
  "C87": [
    "                 ",
    "        ___      ",
    "       /\\  \\     ",
    "       \\:\\  \\    ",
    "        \\:\\  \\   ",
    "    ___  \\:\\__\\  ",
    "   /\\  \\ |:|  |  ",
    "   \\:\\  \\|:|  |  ",
    "    \\:\\__|:|__|  ",
    "     \\::::/__/   ",
    "      ~~~~        "
  ],
  "C88": [
    "        ___      ",
    "       /\\  \\     ",
    "      _\\:\\  \\    ",
    "     /\\ \\:\\  \\   ",
    "    _\\:\\ \\:\\  \\  ",
    "   /\\ \\:\\ \\:\\__\\ ",
    "   \\:\\ \\:\\/:/  / ",
    "    \\:\\ \\::/  /  ",
    "     \\:\\/:/  /   ",
    "      \\::/  /    ",
    "       \\/__/      "
  ],
  "C89": [
    "        ___       ",
    "       /|  |      ",
    "      |:|  |      ",
    "      |:|  |      ",
    "    __|:|__|      ",
    "   /::::\\__\\_____ ",
    "   ~~~~\\::::/___/ ",
    "       |:|~~|     ",
    "       |:|  |     ",
    "       |:|__|     ",
    "       |/__/       "
  ],
  "C90": [
    "               ",
    "               ",
    "        ___    ",
    "       /|  |   ",
    "      |:|  |   ",
    "      |:|  |   ",
    "    __|:|__|   ",
    "   /::::\\  \\   ",
    "   ~~~~\\:\\  \\  ",
    "        \\:\\__\\ ",
    "         \\/__/  "
  ],
  "C91": [
    "        ___      ",
    "       /\\__\\     ",
    "      /::|  |    ",
    "     /:/:|  |    ",
    "    /:/|:|  |__  ",
    "   /:/ |:| /\\__\\ ",
    "   \\/__|:|/:/  / ",
    "       |:/:/  /  ",
    "       |::/  /   ",
    "       |:/  /    ",
    "       |/__/      "
  ],
  "C92": [
    "   ",
    "   ",
    "   ",
    "   ",
    "   ",
    "   ",
    "   ",
    "   ",
    "   ",
    "   ",
    "    "
  ],
  "C93": [
    "   ",
    "   ",
    "   ",
    "   ",
    "   ",
    "   ",
    "   ",
    "   ",
    "   ",
    "   ",
    "    "
  ],
  "C94": [
    "   ",
    "   ",
    "   ",
    "   ",
    "   ",
    "   ",
    "   ",
    "   ",
    "   ",
    "   ",
    "    "
  ],
  "C95": [
    "   ",
    "   ",
    "   ",
    "   ",
    "   ",
    "   ",
    "   ",
    "   ",
    "   ",
    "   ",
    "    "
  ],
  "C96": [
    "   ",
    "   ",
    "   ",
    "   ",
    "   ",
    "   ",
    "   ",
    "   ",
    "   ",
    "   ",
    "    "
  ],
  "C97": [
    "   ",
    "   ",
    "   ",
    "   ",
    "   ",
    "   ",
    "   ",
    "   ",
    "   ",
    "   ",
    "    "
  ],
  "C98": [
    "   ",
    "   ",
    "   ",
    "   ",
    "   ",
    "   ",
    "   ",
    "   ",
    "   ",
    "   ",
    "    "
  ],
  "C99": [
    "   ",
    "   ",
    "   ",
    "   ",
    "   ",
    "   ",
    "   ",
    "   ",
    "   ",
    "   ",
    "    "
  ],
  "C100": [
    "   ",
    "   ",
    "   ",
    "   ",
    "   ",
    "   ",
    "   ",
    "   ",
    "   ",
    "   ",
    "    "
  ],
  "C101": [
    "   ",
    "   ",
    "   ",
    "   ",
    "   ",
    "   ",
    "   ",
    "   ",
    "   ",
    "   ",
    "    "
  ],
  "C102": [
    "   ",
    "   ",
    "   ",
    "   ",
    "   ",
    "   ",
    "   ",
    "   ",
    "   ",
    "   ",
    "    "
  ]
}