{
  "buffer": [
    " `-'  @",
    "  "
  ],
  "C1": [
    "     ",
    "    ",
    "    ",
    "     ",
    "     ",
    "      "
  ],
  "C2": [
    " /\\  ",
    " )(  ",
    " \\/  ",
    " :;  ",
    "      ",
    "       "
  ],
  "C3": [
    " ; ;  ",
    "      ",
    "      ",
    "       ",
    "       ",
    "        "
  ],
  "C4": [
    "  . .   ",
    " -|-|-  ",
    " -|-|-  ",
    "  ' `   ",
    "         ",
    "          "
  ],
  "C5": [
    "       ",
    " ,|.  ",
    " `+.  ",
    " `|'  ",
    "       ",
    "        "
  ],
  "C6": [
    "         ",
    " ,. ,   ",
    " `'/,.  ",
    "  ' `'  ",
    "         ",
    "          "
  ],
  "C7": [
    "        ",
    " ,.    ",
    " >-:,  ",
    " `-'`  ",
    "        ",
    "         "
  ],
  "C8": [
    " .  ",
    " '  ",
    "    ",
    "     ",
    "     ",
    "      "
  ],
  "C9": [
    "  ,-  ",
    " /    ",
    " |    ",
    " \\    ",
    "  `-  ",
    "        "
  ],
  "C10": [
    " -.   ",
    "   \\  ",
    "   |  ",
    "   /  ",
    " -'   ",
    "        "
  ],
  "C11": [
    "       ",
    " . ,  ",
    " -X-  ",
    " ' `  ",
    "       ",
    "        "
  ],
  "C12": [
    "       ",
    "  .   ",
    " -|-  ",
    "  '   ",
    "       ",
    "        "
  ],
  "C13": [
    "      ",
    "     ",
    "    ",
    " :;  ",
    " '   ",
    "       "
  ],
  "C14": [
    "      ",
    "      ",
    " --  ",
    "      ",
    "      ",
    "       "
  ],
  "C15": [
    "      ",
    "     ",
    "    ",
    " :;  ",
    "     ",
    "       "
  ],
  "C16": [
    "       ",
    "   ,  ",
    "  /   ",
    " '    ",
    "       ",
    "        "
  ],
  "C17": [
    "       ",
    " ,-.  ",
    " |/|  ",
    " `-'  ",
    "       ",
    "        "
  ],
  "C18": [
    "      ",
    "  ,  ",
    " '|  ",
    "  `  ",
    "      ",
    "       "
  ],
  "C19": [
    "       ",
    " ,-,  ",
    " /   ",
    " '-`  ",
    "       ",
    "        "
  ],
  "C20": [
    "       ",
    " ,-.  ",
    " -<  ",
    " `-'  ",
    "       ",
    "        "
  ],
  "C21": [
    "       ",
    " ,.  ",
    " {_|  ",
    "  '  ",
    "       ",
    "        "
  ],
  "C22": [
    "       ",
    " .--  ",
    " `-.  ",
    " `-'  ",
    "       ",
    "        "
  ],
  "C23": [
    "       ",
    " ,-.  ",
    " |-.  ",
    " `-'  ",
    "       ",
    "        "
  ],
  "C24": [
    "       ",
    " --,  ",
    " /   ",
    " '    ",
    "       ",
    "        "
  ],
  "C25": [
    "       ",
    " ,-.  ",
    " >-<  ",
    " `-'  ",
    "       ",
    "        "
  ],
  "C26": [
    "       ",
    " ,-.  ",
    " `-|  ",
    " `-'  ",
    "       ",
    "        "
  ],
  "C27": [
    "     ",
    " :;  ",
    "     ",
    " :;  ",
    "     ",
    "       "
  ],
  "C28": [
    "     ",
    " :;  ",
    "     ",
    " :;  ",
    "  ,'  ",
    "       "
  ],
  "C29": [
    "     ",
    " ,  ",
    " <   ",
    " `  ",
    "     ",
    "       "
  ],
  "C30": [
    "     ",
    " __  ",
    " __  ",
    "     ",
    "      ",
    "       "
  ],
  "C31": [
    "      ",
    " .   ",
    " >  ",
    " '   ",
    "      ",
    "       "
  ],
  "C32": [
    " ,-.  ",
    " ` )  ",
    "  (   ",
    "  o   ",
    "       ",
    "        "
  ],
  "C33": [
    "  ,-.   ",
    " /,-.\\  ",
    " |,-||  ",
    " \\`-^/  ",
    "  `-'   ",
    "          "
  ],
  "C34": [
    "     ,.    ",
    "   / |    ",
    "   /~~|-.  ",
    " ,'   `-'  ",
    "            ",
    "             "
  ],
  "C35": [
    " ,-,---.  ",
    "  '|___/  ",
    "  ,|   \\  ",
    " `-^---'  ",
    "           ",
    "            "
  ],
  "C36": [
    "  ,--.  ",
    " | `-'  ",
    " |   .  ",
    " `--'   ",
    "         ",
    "          "
  ],
  "C37": [
    " .-,--.   ",
    " ' |   \\  ",
    " , |   /  ",
    " `-^--'   ",
    "           ",
    "            "
  ],
  "C38": [
    " .-,--.  ",
    "  `\\__   ",
    "   /     ",
    "  '`--'  ",
    "          ",
    "           "
  ],
  "C39": [
    " .-,--'  ",
    "  \\|__   ",
    "   |     ",
    "  `'     ",
    "          ",
    "           "
  ],
  "C40": [
    " ,---.   ",
    " |  -'   ",
    " |  ,-'  ",
    " `---|   ",
    "  ,-.|   ",
    "  `-+'    "
  ],
  "C41": [
    " ,-_/,.  ",
    " ' |_|/  ",
    "  /| |   ",
    "  `' `'  ",
    "          ",
    "           "
  ],
  "C42": [
    " ,-_/  ",
    " '  |  ",
    " .^ |  ",
    " `--'  ",
    "        ",
    "         "
  ],
  "C43": [
    " ,-_/  ",
    " '  |  ",
    "    |  ",
    "    |  ",
    " /` |  ",
    " `--'   "
  ],
  "C44": [
    " ,-, ,  ",
    "  )|/   ",
    "   |\\   ",
    "  ,' `  ",
    "         ",
    "          "
  ],
  "C45": [
    "  ,    ",
    "  )    ",
    " /     ",
    " `--'  ",
    "        ",
    "         "
  ],
  "C46": [
    " ,-,-,-.    ",
    " `,| | |    ",
    "   | ; | .  ",
    "   '   `-'  ",
    "             ",
    "              "
  ],
  "C47": [
    " ,-,-.    ",
    " ` | |    ",
    "   | |-.  ",
    "  ,' `-'  ",
    "           ",
    "            "
  ],
  "C48": [
    " ,,--.  ",
    " |`, |  ",
    " |   |  ",
    " `---'  ",
    "         ",
    "          "
  ],
  "C49": [
    " .-,--.  ",
    "  '|__/  ",
    "  ,|     ",
    "  `'     ",
    "          ",
    "           "
  ],
  "C50": [
    " ,,--.  ",
    " |`. |  ",
    " |  .|  ",
    " `---\\  ",
    "       ` ",
    "          "
  ],
  "C51": [
    " .-,--.  ",
    "  `|__/  ",
    "  )| \\   ",
    "  `'  `  ",
    "          ",
    "           "
  ],
  "C52": [
    " .---.  ",
    " \\___   ",
    "     \\  ",
    " `---'  ",
    "         ",
    "          "
  ],
  "C53": [
    "  ,--,--' ",
    " `- |    ",
    "  , |    ",
    "  `-'    ",
    "          ",
    "           "
  ],
  "C54": [
    " ,-.  .    ",
    "   |  |    ",
    "   |  | .  ",
    "   `--^-'  ",
    "            ",
    "             "
  ],
  "C55": [
    " ,.   ,.  ",
    " `|  /    ",
    "  | /     ",
    "  `'      ",
    "           ",
    "            "
  ],
  "C56": [
    " ,.   ,   ,.  ",
    " `|  /|  /    ",
    "  | / | /     ",
    "  `'  `'      ",
    "               ",
    "                "
  ],
  "C57": [
    " ,.  ,.  ",
    " ` \\/ '  ",
    "   /\\    ",
    " `'  `'  ",
    "          ",
    "           "
  ],
  "C58": [
    " .  .  ",
    " |  |  ",
    " |  |  ",
    " `--|  ",
    " .- |  ",
    " `--'   "
  ],
  "C59": [
    " ,-_/  ",
    "   /   ",
    "  /    ",
    " /--,  ",
    "        ",
    "         "
  ],
  "C60": [
    " .-  ",
    " |   ",
    " |   ",
    " |   ",
    " `-  ",
    "       "
  ],
  "C61": [
    "       ",
    " .    ",
    "  \\   ",
    "   `  ",
    "       ",
    "        "
  ],
  "C62": [
    " -.  ",
    "  |  ",
    "  |  ",
    "  |  ",
    " -'  ",
    "       "
  ],
  "C63": [
    "      ",
    " /\\  ",
    "     ",
    "     ",
    "      ",
    "       "
  ],
  "C64": [
    "   ",
    "    ",
    "    ",
    "   ",
    "  ~~ ",
    "      "
  ],
  "C65": [
    " .   ",
    "  `  ",
    "     ",
    "      ",
    "      ",
    "       "
  ],
  "C66": [
    "       ",
    " ,-.  ",
    " ,-|  ",
    " `-^  ",
    "       ",
    "        "
  ],
  "C67": [
    " .    ",
    " |-.  ",
    " | |  ",
    " ^-'  ",
    "       ",
    "        "
  ],
  "C68": [
    "       ",
    " ,-.  ",
    " |    ",
    " `-'  ",
    "       ",
    "        "
  ],
  "C69": [
    "   .  ",
    " ,-|  ",
    " | |  ",
    " `-^  ",
    "       ",
    "        "
  ],
  "C70": [
    "       ",
    " ,-.  ",
    " |-'  ",
    " `-'  ",
    "       ",
    "        "
  ],
  "C71": [
    "     ",
    " ,\"  ",
    " |-  ",
    " |   ",
    " '   ",
    "       "
  ],
  "C72": [
    "       ",
    " ,-.  ",
    " | |  ",
    " `-|  ",
    "  ,|  ",
    "  `'   "
  ],
  "C73": [
    " .    ",
    " |-.  ",
    " | |  ",
    " ' '  ",
    "       ",
    "        "
  ],
  "C74": [
    "     ",
    " .  ",
    " |  ",
    " '  ",
    "     ",
    "      "
  ],
  "C75": [
    "      ",
    "  .  ",
    "  |  ",
    "  |  ",
    "  |  ",
    " `'   "
  ],
  "C76": [
    " .    ",
    " | ,  ",
    " |<   ",
    " ' `  ",
    "       ",
    "        "
  ],
  "C77": [
    " .   ",
    " |   ",
    " |   ",
    " `'  ",
    "      ",
    "       "
  ],
  "C78": [
    "         ",
    " ,-,-.  ",
    " | | |  ",
    " ' ' '  ",
    "         ",
    "          "
  ],
  "C79": [
    "       ",
    " ,-.  ",
    " | |  ",
    " ' '  ",
    "       ",
    "        "
  ],
  "C80": [
    "       ",
    " ,-.  ",
    " | |  ",
    " `-'  ",
    "       ",
    "        "
  ],
  "C81": [
    "       ",
    " ,-.  ",
    " | |  ",
    " |-'  ",
    " |    ",
    " '     "
  ],
  "C82": [
    "       ",
    " ,-.  ",
    " | |  ",
    " `-|  ",
    "   |  ",
    "   `   "
  ],
  "C83": [
    "       ",
    " ,-.  ",
    " |    ",
    " '    ",
    "       ",
    "        "
  ],
  "C84": [
    "       ",
    " ,-.  ",
    " `-.  ",
    " `-'  ",
    "       ",
    "        "
  ],
  "C85": [
    " .   ",
    " |-  ",
    " |   ",
    " `'  ",
    "      ",
    "       "
  ],
  "C86": [
    "       ",
    " . .  ",
    " | |  ",
    " `-^  ",
    "       ",
    "        "
  ],
  "C87": [
    "        ",
    " .  ,  ",
    " | /   ",
    " `'    ",
    "        ",
    "         "
  ],
  "C88": [
    "         ",
    " . , ,  ",
    " |/|/   ",
    " ' '    ",
    "         ",
    "          "
  ],
  "C89": [
    "       ",
    " . ,  ",
    "  X   ",
    " ' `  ",
    "       ",
    "        "
  ],
  "C90": [
    "       ",
    " . .  ",
    " | |  ",
    " `-|  ",
    "  /|  ",
    " `-'   "
  ],
  "C91": [
    "       ",
    " ,_,  ",
    "  /   ",
    " '\"'  ",
    "       ",
    "        "
  ],
  "C92": [
    " .-  ",
    "  )  ",
    " <   ",
    "  )  ",
    " '-  ",
    "       "
  ],
  "C93": [
    " |  ",
    " |  ",
    " |  ",
    " |  ",
    " |  ",
    "      "
  ],
  "C94": [
    " -,  ",
    " (   ",
    "  >  ",
    " (   ",
    " -`  ",
    "       "
  ],
  "C95": [
    "         ",
    " ,'`,'  ",
    "       ",
    "       ",
    "        ",
    "          "
  ],
  "C96": [
    "    o,.o   ",
    "    / |    ",
    "   /~~|-.  ",
    " ,'   `-'  ",
    "            ",
    "             "
  ],
  "C97": [
    "  o_o   ",
    " (   )  ",
    " |   |  ",
    " `---'  ",
    "         ",
    "          "
  ],
  "C98": [
    " . o o    ",
    " '\\  |    ",
    "  |  | .  ",
    "  `--^-'  ",
    "           ",
    "            "
  ],
  "C99": [
    " o o  ",
    " ,-.  ",
    " ,-|  ",
    " `-^  ",
    "       ",
    "        "
  ],
  "C100": [
    " o o  ",
    " ,-.  ",
    " | |  ",
    " `-'  ",
    "       ",
    "        "
  ],
  "C101": [
    " o o  ",
    " . .  ",
    " | |  ",
    " `-^  ",
    "       ",
    "        "
  ],
  "C102": [
    "   ,-.   ",
    "   |_/   ",
    "  ,| .\\  ",
    " `-' `'  ",
    "          ",
    "           "
  ],
  "C103": [
    "  128",
    "  ,-,--.  ",
    " /  \\__   ",
    " \\  /     ",
    "  `'`--'  ",
    "           "
  ],
  "C104": [
    "           @",
    "  129",
    "         ",
    " ,-,-.  ",
    " | |-'  ",
    " `-^-'  "
  ],
  "C105": [
    "         ",
    "         @",
    "  130",
    " .o o  ",
    " |  |  ",
    " |  |  "
  ],
  "C106": [
    " `--|  ",
    " ,. /  ",
    " `-'   @",
    "  137",
    " .`.,',  ",
    " .`/\\',  "
  ],
  "C107": [
    " -({})-  ",
    " ',\\/.`  ",
    " ','`.`  ",
    "          @",
    "  138",
    "         "
  ],
  "C108": [
    " .oo0O  ",
    " ( Y )  ",
    "  \\ (   ",
    "   \\_)  ",
    "         @",
    "  139"
  ],
  "C109": [
    "    _   ",
    "   / )  ",
    "  / (   ",
    " (   )  ",
    " `ooo0  ",
    "          "
  ],
  "C110": [
    "  140",
    "   _     ",
    " ( \\    ",
    "  ) \\   ",
    " (   )  ",
    " 0ooo,  "
  ],
  "C111": [
    "         @",
    "  141",
    "         ",
    " O0oo,  ",
    " ( Y )  ",
    "  ) /   "
  ],
  "C112": [
    " (_/    ",
    "         @",
    "  142",
    " o   o  ",
    " |\\^/|  ",
    "  \\Y/   "
  ],
  "C113": [
    "  /_\\   ",
    " _/ \\_  ",
    "         @",
    "  144",
    "   _______     ",
    " (_,---._)    "
  ],
  "C114": [
    "  / (O) \\`~.  ",
    "  \\_____/~~'  ",
    "               ",
    "               @",
    "  145",
    "  _____    "
  ],
  "C115": [
    " |ooo[_]|  ",
    " |ooo| ||  ",
    " |ooo|_||  ",
    " |___[_]|  ",
    "            @",
    "  146"
  ],
  "C116": [
    "  ________    ",
    " |\\       \\   ",
    " | }-------}  ",
    "  \\| o o o |  ",
    "   `-------'  ",
    "                "
  ],
  "C117": [
    "  147",
    "   ___    ",
    " {~._.~}  ",
    "  ( Y )   ",
    " ()~*~()  ",
    " (_)-(_)  "
  ],
  "C118": [
    "           @",
    "  148",
    "    |\\  ",
    "    |\\  ",
    " (`')   ",
    "  `'    "
  ],
  "C119": [
    "        ",
    "         @",
    "  161",
    " ,.  ",
    " `'  ",
    " /\\  "
  ],
  "C120": [
    " )(  ",
    " \\/  ",
    "      @",
    "  162",
    "  .   ",
    " ,+.  "
  ],
  "C121": [
    " ||   ",
    " `+'  ",
    "  '   ",
    "       @",
    "  163",
    "   ,-,  "
  ],
  "C122": [
    " _|_    ",
    "  )     ",
    " '--'   ",
    "         ",
    "         @",
    "  164"
  ],
  "C123": [
    "       ",
    " \\-/  ",
    " | |  ",
    " /-\\  ",
    "       ",
    "        "
  ],
  "C124": [
    "  165",
    " . ,  ",
    " _Y_  ",
    " -|-  ",
    "  '   ",
    "       "
  ],
  "C125": [
    "       @",
    "  166",
    " |  ",
    " |  ",
    "    ",
    " |  "
  ],
  "C126": [
    " |  ",
    "   @",
    "  167",
    " ,-.  ",
    " >-.  ",
    " `-<  "
  ],
  "C127": [
    " `-'  ",
    "       ",
    "       @",
    "  168",
    " o o  ",
    "     "
  ],
  "C128": [
    "      ",
    "       ",
    "       ",
    "       @",
    "  169",
    "  ,-.   "
  ],
  "C129": [
    " /,-.\\  ",
    " ||  |  ",
    " \\`-'/  ",
    "  `-'   ",
    "         @",
    "  170"
  ],
  "C130": [
    "  _\\  ",
    " (_|  ",
    " ~~~  ",
    "      ",
    "       ",
    "        "
  ],
  "C131": [
    "  171",
    "       ",
    "  ,,  ",
    " <<   ",
    "  ``  ",
    "       "
  ],
  "C132": [
    "       @",
    "  172",
    "        ",
    " ___   ",
    "    |  ",
    "        "
  ],
  "C133": [
    "        ",
    "        @",
    "  173",
    "       ",
    " ___  ",
    "     "
  ],
  "C134": [
    "       ",
    "       ",
    "       @",
    "  174",
    "  ,-.   ",
    " /,-.\\  "
  ],
  "C135": [
    " ||_/|  ",
    " \\| \\/  ",
    "  `-'   ",
    "         @",
    "  175",
    " __  "
  ],
  "C136": [
    "    ",
    "     ",
    "      ",
    "      ",
    "      @",
    "  176"
  ],
  "C137": [
    " ,.  ",
    " `'  ",
    "     ",
    "      ",
    "      ",
    "       "
  ],
  "C138": [
    "  177",
    "       ",
    " _|_  ",
    "  |   ",
    " ---  ",
    "       "
  ],
  "C139": [
    "       @",
    "  178",
    " ,.  ",
    "  /  ",
    " \"\"  ",
    "     "
  ],
  "C140": [
    "      ",
    "      @",
    "  179",
    " ,.  ",
    "  +  ",
    " `'  "
  ],
  "C141": [
    "     ",
    "      ",
    "      @",
    "  180",
    " ,'  ",
    "     "
  ],
  "C142": [
    "     ",
    "      ",
    "      ",
    "      @",
    "  181",
    "       "
  ],
  "C143": [
    " . .  ",
    " | |  ",
    " |-^  ",
    "  |    ",
    "  '    @",
    "  182"
  ],
  "C144": [
    "  ,-,,  ",
    " (  ||  ",
    "  `-||  ",
    "    ||  ",
    "   -^-  ",
    "          "
  ],
  "C145": [
    "  183",
    "     ",
    "     ",
    " o  ",
    "     ",
    "     "
  ],
  "C146": [
    "     @",
    "  184",
    "      ",
    "      ",
    "      ",
    "  .  "
  ],
  "C147": [
    " `'  ",
    "      @",
    "  185",
    "  ,  ",
    " '|  ",
    "     "
  ],
  "C148": [
    "     ",
    "      ",
    "      @",
    "  186",
    " ,.  ",
    " `'  "
  ],
  "C149": [
    " \"\"  ",
    "     ",
    "      ",
    "      @",
    "  187",
    "       "
  ],
  "C150": [
    " ..   ",
    "  >>  ",
    " ''   ",
    "       ",
    "       @",
    "  188"
  ],
  "C151": [
    "  ,  ,  ",
    " '| /   ",
    "   /    ",
    "  /  ,  ",
    " '  '+  ",
    "         "
  ],
  "C152": [
    "  189",
    "  ,  ,  ",
    " '| /   ",
    "   /    ",
    "  / ,.  ",
    " '   /  "
  ],
  "C153": [
    "    \"\"  @",
    "  190",
    " ,.  ,  ",
    "  + /   ",
    " `'/    ",
    "  /  ,  "
  ],
  "C154": [
    " '  '+  ",
    "         @",
    "  191",
    "       ",
    "  o   ",
    "  )   "
  ],
  "C155": [
    " ( .  ",
    " `-'  ",
    "       @",
    "  192",
    "    \\,.    ",
    "    /`|    "
  ],
  "C156": [
    "   /~~(-.  ",
    " -'    `'  ",
    "            ",
    "            @",
    "  193",
    "     ,/    "
  ],
  "C157": [
    "    /'|    ",
    "   /~~|-.  ",
    " `'   `-'  ",
    "            ",
    "            @",
    "  194"
  ],
  "C158": [
    "    /^\\    ",
    "    /^\\    ",
    "   /~~| .  ",
    " ,'   `-'  ",
    "            ",
    "             "
  ],
  "C159": [
    "  195",
    "   ,'`,'   ",
    "    / \\    ",
    "   /~~| ,  ",
    "  '   `-'  ",
    "            "
  ],
  "C160": [
    "            @",
    "  196",
    "    o,.o   ",
    "    / |    ",
    "   /~~| ,  ",
    " ,'   `'   "
  ],
  "C161": [
    "            ",
    "            @",
    "  197",
    "     O     ",
    "    / \\    ",
    "  ,/~~|    "
  ],
  "C162": [
    " `'   `-.  ",
    "            ",
    "            @",
    "  198",
    "     ,,--.  ",
    "    / \\__   "
  ],
  "C163": [
    " / /~~|     ",
    " `'   `--'  ",
    "             ",
    "             @",
    "  199",
    "  ,--.  "
  ],
  "C164": [
    " | '-'  ",
    " |   .  ",
    "  `-/   ",
    "  `'    ",
    "         @",
    "  200"
  ],
  "C165": [
    " ,-._\\.  ",
    " ' |__   ",
    "  /|     ",
    "  `^--'  ",
    "          ",
    "           "
  ],
  "C166": [
    "  201",
    " ,-._/.  ",
    "  '|__   ",
    "   |     ",
    "  `^--'  ",
    "          "
  ],
  "C167": [
    "          @",
    "  202",
    "   /_\\.  ",
    " ''|__   ",
    "  ,|     ",
    "  `^--'  "
  ],
  "C168": [
    "          ",
    "          @",
    "  203",
    "  ,o_o.  ",
    "  \\|__   ",
    "   |     "
  ],
  "C169": [
    "  ,^--'  ",
    "          ",
    "          @",
    "  204",
    "  _\\,  ",
    " ' \"|  "
  ],
  "C170": [
    " ., |  ",
    " `--'  ",
    "        ",
    "        @",
    "  205",
    "  _/,  "
  ],
  "C171": [
    " ' \"|  ",
    "    |  ",
    " `--'  ",
    "        ",
    "        @",
    "  206"
  ],
  "C172": [
    "  /^\\  ",
    " ,^\"|  ",
    "  , |  ",
    " `--'  ",
    "        ",
    "         "
  ],
  "C173": [
    "  207",
    " o_o,  ",
    " ' \"|  ",
    " ., |  ",
    " `--'  ",
    "        "
  ],
  "C174": [
    "        @",
    "  208",
    " ~.--.   ",
    " _|_  \\  ",
    "  |   /  ",
    " ,^--'   "
  ],
  "C175": [
    "          ",
    "          @",
    "  209",
    "  ,'`,'   ",
    " .'v\".    ",
    "   | | \\  "
  ],
  "C176": [
    "  ,' `-'  ",
    "           ",
    "           @",
    "  210",
    "  _\\    ",
    " |  `)  "
  ],
  "C177": [
    " |   |  ",
    " `--'   ",
    "         ",
    "         @",
    "  211",
    " ,- /,  "
  ],
  "C178": [
    " | ' |  ",
    " |   |  ",
    "  `--'  ",
    "         ",
    "         @",
    "  212"
  ],
  "C179": [
    "  /_\\   ",
    " ,' `.  ",
    " |   |  ",
    "  `--'  ",
    "         ",
    "          "
  ],
  "C180": [
    "  213",
    " ,'`,'  ",
    " ,---.  ",
    " |   |  ",
    " `---'  ",
    "         "
  ],
  "C181": [
    "         @",
    "  214",
    "  o_o   ",
    " (   )  ",
    " |   |  ",
    " `---'  "
  ],
  "C182": [
    "         ",
    "         @",
    "  215",
    "      ",
    " \\ /  ",
    "  X   "
  ],
  "C183": [
    " / \\  ",
    "       ",
    "       @",
    "  216",
    " ,--/  ",
    " | /|  "
  ],
  "C184": [
    " |/ |  ",
    " /--'  ",
    "        ",
    "        @",
    "  217",
    " .,\\ .    "
  ],
  "C185": [
    " `|  |    ",
    "  |  | _  ",
    "  `--^'   ",
    "           ",
    "           @",
    "  218"
  ],
  "C186": [
    " ., /.    ",
    " )|  |    ",
    "  |  |\\   ",
    "  `--^-'  ",
    "           ",
    "            "
  ],
  "C187": [
    "  219",
    "  /^\\    ",
    " |  |    ",
    " |  |    ",
    " `--^.'  ",
    "          "
  ],
  "C188": [
    "          @",
    "  220",
    "  o o    ",
    " |  |    ",
    " |  | .  ",
    " `--^-'  "
  ],
  "C189": [
    "          ",
    "          @",
    "  221",
    " . /.  ",
    " |  |  ",
    " |  |  "
  ],
  "C190": [
    " `--|  ",
    " ,. /  ",
    " `-'   @",
    "  222",
    " ,      ",
    " |--.   "
  ],
  "C191": [
    " |   )  ",
    " |--'   ",
    " |      ",
    " ^-     @",
    "  223",
    "   ,-.   "
  ],
  "C192": [
    "   |_/   ",
    "  ,| .\\  ",
    " `-' `'  ",
    "          ",
    "          @",
    "  224"
  ],
  "C193": [
    "  \\   ",
    " ,-.  ",
    " ,-|  ",
    " `-^  ",
    "       ",
    "        "
  ],
  "C194": [
    "  225",
    "  /   ",
    " ,-.  ",
    " ,-|  ",
    " `-^  ",
    "       "
  ],
  "C195": [
    "       @",
    "  226",
    " ,^.  ",
    " ,-.  ",
    " ,-|  ",
    " `-^  "
  ],
  "C196": [
    "       ",
    "       @",
    "  227",
    " v^v  ",
    " ,-.  ",
    " ,-|  "
  ],
  "C197": [
    " `-^  ",
    "       ",
    "       @",
    "  228",
    " o o  ",
    " ,-.  "
  ],
  "C198": [
    " ,-|  ",
    " `-^  ",
    "       ",
    "       @",
    "  229",
    "  O   "
  ],
  "C199": [
    " ,-.  ",
    " ,-|  ",
    " `-^  ",
    "       ",
    "       @",
    "  230"
  ],
  "C200": [
    "         ",
    " ,-,-.  ",
    " ,-|-'  ",
    " `-^-'  ",
    "         ",
    "          "
  ],
  "C201": [
    "  231",
    "       ",
    " ,-.  ",
    " |    ",
    " `v'  ",
    "  `'   "
  ],
  "C202": [
    "       @",
    "  232",
    "  \\   ",
    " ,-.  ",
    " |-'  ",
    " `-'  "
  ],
  "C203": [
    "       ",
    "       @",
    "  233",
    "  /   ",
    " ,-.  ",
    " |-'  "
  ],
  "C204": [
    " `-'  ",
    "       ",
    "       @",
    "  234",
    " ,^.  ",
    " ,-.  "
  ],
  "C205": [
    " |-'  ",
    " `-'  ",
    "       ",
    "       @",
    "  235",
    " o o  "
  ],
  "C206": [
    " ,-.  ",
    " |-'  ",
    " `-'  ",
    "       ",
    "       @",
    "  236"
  ],
  "C207": [
    " \\  ",
    " .  ",
    " |  ",
    " '  ",
    "     ",
    "      "
  ],
  "C208": [
    "  237",
    " /  ",
    " .  ",
    " |  ",
    " '  ",
    "     "
  ],
  "C209": [
    "     @",
    "  238",
    " ^  ",
    " .  ",
    " |  ",
    " '  "
  ],
  "C210": [
    "     ",
    "     @",
    "  239",
    " o o  ",
    "  .   ",
    "  |   "
  ],
  "C211": [
    "  '   ",
    "       ",
    "       @",
    "  240",
    " ><   ",
    " ,-\\  "
  ],
  "C212": [
    " | |  ",
    " `-'  ",
    "       ",
    "       @",
    "  241",
    " v^v  "
  ],
  "C213": [
    " ,-.  ",
    " | |  ",
    " ' '  ",
    "       ",
    "       @",
    "  242"
  ],
  "C214": [
    "  \\   ",
    " ,-.  ",
    " | |  ",
    " `-'  ",
    "       ",
    "        "
  ],
  "C215": [
    "  243",
    "  /   ",
    " ,-.  ",
    " | |  ",
    " `-'  ",
    "       "
  ],
  "C216": [
    "       @",
    "  244",
    " ,^.  ",
    " ,-.  ",
    " | |  ",
    " `-'  "
  ],
  "C217": [
    "       ",
    "       @",
    "  245",
    " v^v  ",
    " ,-.  ",
    " | |  "
  ],
  "C218": [
    " `-'  ",
    "       ",
    "       @",
    "  246",
    " o o  ",
    " ,-.  "
  ],
  "C219": [
    " | |  ",
    " `-'  ",
    "       ",
    "       @",
    "  247",
    "       "
  ],
  "C220": [
    "  o   ",
    " ---  ",
    "  o   ",
    "       ",
    "       @",
    "  248"
  ],
  "C221": [
    "      ",
    " ,-/  ",
    " |/|  ",
    " /-'  ",
    "       ",
    "        "
  ],
  "C222": [
    "  249",
    "  \\   ",
    " . .  ",
    " | |  ",
    " `-^  ",
    "       "
  ],
  "C223": [
    "       @",
    "  250",
    "  /   ",
    " . .  ",
    " | |  ",
    " `-^  "
  ],
  "C224": [
    "       ",
    "       @",
    "  251",
    " ,^.  ",
    " . .  ",
    " | |  "
  ],
  "C225": [
    " `-^  ",
    "       ",
    "       @",
    "  252",
    " o o  ",
    " . .  "
  ],
  "C226": [
    " | |  ",
    " `-^  ",
    "       ",
    "       @",
    "  253",
    "  /   "
  ],
  "C227": [
    " . .  ",
    " | |  ",
    " `-|  ",
    "  /|  ",
    " `-'  @",
    "  254"
  ],
  "C228": [
    "       ",
    " |-.  ",
    " |-'  ",
    " ^    ",
    "       ",
    "        "
  ],
  "C229": [
    "  255",
    " o o  ",
    " . .  ",
    " | |  ",
    " `-|  ",
    "  /|  "
  ]
}